drux/__init__.py
drux/base_model.py
drux/first_order.py
drux/higuchi.py
drux/messages.py
drux/params.py
drux/weibull.py
drux/zero_order.py
drux-0.3.dist-info/licenses/AUTHORS.md
drux-0.3.dist-info/licenses/LICENSE
drux-0.3.dist-info/METADATA
drux-0.3.dist-info/WHEEL
drux-0.3.dist-info/top_level.txt
drux-0.3.dist-info/RECORD
